fontsy/__init__.py
fontsy-0.1.7.dist-info/METADATA
fontsy-0.1.7.dist-info/WHEEL
fontsy-0.1.7.dist-info/entry_points.txt
fontsy-0.1.7.dist-info/RECORD
