Metadata-Version: 2.4
Name: fontsy
Version: 0.1.7
Summary: An ASCII font explorer
Author-email: Andre Ratzenberger <andre.ratzenberger@whiteduck.de>
Requires-Python: >=3.12
Requires-Dist: art>=6.4
Requires-Dist: pyperclip>=1.9.0
Requires-Dist: rich>=14.0.0
